{"chunk_definitions":[{"row":10,"row_count":1,"visible":true,"expansion_state":0,"options":{"engine":"r","label":"setup","include":false,"dev":"png"},"document_id":"4703C0CA","chunk_id":"csetup_chunk","chunk_label":"setup"},{"row":25,"row_count":1,"visible":true,"expansion_state":0,"options":{"engine":"r","label":"read in data","dev":"png"},"document_id":"4703C0CA","chunk_id":"c147uadv8ikqk","chunk_label":"read in data"},{"row":35,"row_count":1,"visible":true,"expansion_state":0,"options":{"engine":"r","label":"unnamed-chunk-24","dev":"png"},"document_id":"4703C0CA","chunk_id":"ctoywmkz0egil","chunk_label":"unnamed-chunk-1"},{"row":40,"row_count":1,"visible":true,"expansion_state":0,"options":{"engine":"r","label":"Figure 1","dev":"png"},"document_id":"4703C0CA","chunk_id":"c1tzl5odgbjhs","chunk_label":"Figure 1"},{"row":74,"row_count":1,"visible":true,"expansion_state":0,"options":{"engine":"r","label":"unnamed-chunk-25","dev":"png"},"document_id":"4703C0CA","chunk_id":"cc51hk7sxzfn2","chunk_label":"unnamed-chunk-2"},{"row":108,"row_count":1,"visible":true,"expansion_state":0,"options":{"engine":"r","label":"Figure 2","dev":"png"},"document_id":"4703C0CA","chunk_id":"cf5ttor51empj","chunk_label":"Figure 2"},{"row":113,"row_count":1,"visible":true,"expansion_state":0,"options":{"engine":"r","label":"unnamed-chunk-26","dev":"png"},"document_id":"4703C0CA","chunk_id":"cmonvrcbbf4lk","chunk_label":"unnamed-chunk-3"},{"row":138,"row_count":1,"visible":true,"expansion_state":0,"options":{"engine":"r","label":"Figure 3","dev":"png"},"document_id":"4703C0CA","chunk_id":"cn5a0hdyberhb","chunk_label":"Figure 3"},{"row":160,"row_count":1,"visible":true,"expansion_state":0,"options":{"engine":"r","label":"Figure 7 column i","dev":"png"},"document_id":"4703C0CA","chunk_id":"cnqxbq2nhe6dn","chunk_label":"Figure 7 column i"},{"row":240,"row_count":1,"visible":true,"expansion_state":0,"options":{"engine":"r","label":"Yeo-Johnson transform; fitting linear regression and Variance Inflation Factors","dev":"png"},"document_id":"4703C0CA","chunk_id":"co7gzsg0rzmjl","chunk_label":"Yeo-Johnson transform; fitting linear regression and Variance Inflation Factors"},{"row":278,"row_count":1,"visible":true,"expansion_state":0,"options":{"engine":"r","label":"Visualising clustering of linear regression residuals","dev":"png"},"document_id":"4703C0CA","chunk_id":"cibenbouiqqxr","chunk_label":"Visualising clustering of linear regression residuals"},{"row":326,"row_count":1,"visible":true,"expansion_state":0,"options":{"engine":"r","label":"unnamed-chunk-101","dev":"png"},"document_id":"4703C0CA","chunk_id":"cgpmjrw633zec","chunk_label":"unnamed-chunk-4"},{"row":358,"row_count":1,"visible":true,"expansion_state":0,"options":{"engine":"r","label":"unnamed-chunk-29","dev":"png"},"document_id":"4703C0CA","chunk_id":"cu6ti3afwu2yh","chunk_label":"unnamed-chunk-5"},{"row":385,"row_count":1,"visible":true,"expansion_state":0,"options":{"engine":"r","label":"unnamed-chunk-104","dev":"png"},"document_id":"4703C0CA","chunk_id":"cglm6iz3okcg8","chunk_label":"unnamed-chunk-6"},{"row":394,"row_count":1,"visible":true,"expansion_state":0,"options":{"engine":"r","label":"Figure 6","dev":"png"},"document_id":"4703C0CA","chunk_id":"cb6eti7yd4kx7","chunk_label":"Figure 6"},{"row":424,"row_count":1,"visible":true,"expansion_state":0,"options":{"engine":"r","label":"unnamed-chunk-112","dev":"png"},"document_id":"4703C0CA","chunk_id":"confml9mkjgar","chunk_label":"calculate contribution terms X*beta"},{"row":496,"row_count":1,"visible":true,"expansion_state":0,"options":{"engine":"r","label":"unnamed-chunk-124","dev":"png"},"document_id":"4703C0CA","chunk_id":"c939qg3h8ys9d","chunk_label":"unnamed-chunk-7"},{"row":563,"row_count":1,"visible":true,"expansion_state":0,"options":{"engine":"r","label":"Figure 10","dev":"png"},"document_id":"4703C0CA","chunk_id":"cxt2lq8u7e9xe","chunk_label":"Figure 10"}],"doc_write_time":1740369107,"working_dir":null,"default_chunk_options":{"echo":true},"chunk_rendered_width":525}